syn/iverilog/0518/axi_pim.v
/*

Copyright (c) 2018 Alex Forencich

Permission is hereby granted, free of charge, to any person obtaining a copy
of this software and associated documentation files (the "Software"), to deal
in the Software without restriction, including without limitation the rights
to use, copy, modify, merge, publish, distribute, sublicense, and/or sell
copies of the Software, and to permit persons to whom the Software is
furnished to do so, subject to the following conditions:

The above copyright notice and this permission notice shall be included in
all copies or substantial portions of the Software.

THE SOFTWARE IS PROVIDED "AS IS", WITHOUT WARRANTY OF ANY KIND, EXPRESS OR
IMPLIED, INCLUDING BUT NOT LIMITED TO THE WARRANTIES OF MERCHANTABILITY
FITNESS FOR A PARTICULAR PURPOSE AND NONINFRINGEMENT. IN NO EVENT SHALL THE
AUTHORS OR COPYRIGHT HOLDERS BE LIABLE FOR ANY CLAIM, DAMAGES OR OTHER
LIABILITY, WHETHER IN AN ACTION OF CONTRACT, TORT OR OTHERWISE, ARISING FROM,
OUT OF OR IN CONNECTION WITH THE SOFTWARE OR THE USE OR OTHER DEALINGS IN
THE SOFTWARE.

*/

// Language: Verilog 2001

`resetall
`timescale 1ns / 1ps
`default_nettype none

/*
 * AXI4 RAM with PIM Model
 */
module axi_pim #
(
    parameter PIM_ADDR_BEGIN = 'h000,
    // Width of data bus in bits
    parameter DATA_WIDTH = 32,
    // Width of address bus in bits
    parameter ADDR_WIDTH = 8,
    // Width of wstrb (width of data bus in words)
    parameter STRB_WIDTH = (DATA_WIDTH/8),
    // Width of ID signal
    parameter ID_WIDTH = 8,
    // Extra pipeline register on output
    parameter PIPELINE_OUTPUT = 0,
    parameter PWIDTH = 32,
    parameter PDEPTH = (1<<ADDR_WIDTH)
)
(
    input  wire                   clk,
    input  wire                   rst,

    input  wire [ID_WIDTH-1:0]    s_axi_awid,
    input  wire [ADDR_WIDTH-1:0]  s_axi_awaddr,
    input  wire [7:0]             s_axi_awlen,
    input  wire [2:0]             s_axi_awsize,
    input  wire [1:0]             s_axi_awburst,
    input  wire                   s_axi_awlock,
    input  wire [3:0]             s_axi_awcache,
    input  wire [2:0]             s_axi_awprot,
    input  wire                   s_axi_awvalid,
    output wire                   s_axi_awready,
    input  wire [DATA_WIDTH-1:0]  s_axi_wdata,
    input  wire [STRB_WIDTH-1:0]  s_axi_wstrb,
    input  wire                   s_axi_wlast,
    input  wire                   s_axi_wvalid,
    output wire                   s_axi_wready,
    output wire [ID_WIDTH-1:0]    s_axi_bid,
    output wire [1:0]             s_axi_bresp,
    output wire                   s_axi_bvalid,
    input  wire                   s_axi_bready,
    input  wire [ID_WIDTH-1:0]    s_axi_arid,
    input  wire [ADDR_WIDTH-1:0]  s_axi_araddr,
    input  wire [7:0]             s_axi_arlen,
    input  wire [2:0]             s_axi_arsize,
    input  wire [1:0]             s_axi_arburst,
    input  wire                   s_axi_arlock,
    input  wire [3:0]             s_axi_arcache,
    input  wire [2:0]             s_axi_arprot,
    input  wire                   s_axi_arvalid,
    output wire                   s_axi_arready,
    output wire [ID_WIDTH-1:0]    s_axi_rid,
    output wire [DATA_WIDTH-1:0]  s_axi_rdata,
    output wire [1:0]             s_axi_rresp,
    output wire                   s_axi_rlast,
    output wire                   s_axi_rvalid,
    input  wire                   s_axi_rready,

    output wire [DATA_WIDTH-1:0] mac_out
);

parameter VALID_ADDR_WIDTH = ADDR_WIDTH - $clog2(STRB_WIDTH);
parameter WORD_WIDTH = STRB_WIDTH;
parameter WORD_SIZE = DATA_WIDTH/WORD_WIDTH;

// bus width assertions
initial begin
    if (WORD_SIZE * STRB_WIDTH != DATA_WIDTH) begin
        $error("Error: AXI data width not evenly divisible (instance %m)");
        $finish;
    end

    if (2**$clog2(WORD_WIDTH) != WORD_WIDTH) begin
        $error("Error: AXI word width must be even power of two (instance %m)");
        $finish;
    end
end

localparam [0:0]
    READ_STATE_IDLE = 1'd0,
    READ_STATE_BURST = 1'd1;

reg [0:0] read_state_reg = READ_STATE_IDLE, read_state_next;

localparam [1:0]
    WRITE_STATE_IDLE = 2'd0,
    WRITE_STATE_BURST = 2'd1,
    WRITE_STATE_RESP = 2'd2;

reg [1:0] write_state_reg = WRITE_STATE_IDLE, write_state_next;

reg mem_wr_en;
reg mem_rd_en;

reg [ID_WIDTH-1:0] read_id_reg = {ID_WIDTH{1'b0}}, read_id_next;
reg [ADDR_WIDTH-1:0] read_addr_reg = {ADDR_WIDTH{1'b0}}, read_addr_next;
reg [7:0] read_count_reg = 8'd0, read_count_next;
reg [2:0] read_size_reg = 3'd0, read_size_next;
reg [1:0] read_burst_reg = 2'd0, read_burst_next;
reg [ID_WIDTH-1:0] write_id_reg = {ID_WIDTH{1'b0}}, write_id_next;
reg [ADDR_WIDTH-1:0] write_addr_reg = {ADDR_WIDTH{1'b0}}, write_addr_next;
reg [7:0] write_count_reg = 8'd0, write_count_next;
reg [2:0] write_size_reg = 3'd0, write_size_next;
reg [1:0] write_burst_reg = 2'd0, write_burst_next;

reg s_axi_awready_reg = 1'b0, s_axi_awready_next;
reg s_axi_wready_reg = 1'b0, s_axi_wready_next;
reg [ID_WIDTH-1:0] s_axi_bid_reg = {ID_WIDTH{1'b0}}, s_axi_bid_next;
reg s_axi_bvalid_reg = 1'b0, s_axi_bvalid_next;
reg s_axi_arready_reg = 1'b0, s_axi_arready_next;
reg [ID_WIDTH-1:0] s_axi_rid_reg = {ID_WIDTH{1'b0}}, s_axi_rid_next;
reg [DATA_WIDTH-1:0] s_axi_rdata_reg = {DATA_WIDTH{1'b0}}, s_axi_rdata_next;
reg s_axi_rlast_reg = 1'b0, s_axi_rlast_next;
reg s_axi_rvalid_reg = 1'b0, s_axi_rvalid_next;
reg [ID_WIDTH-1:0] s_axi_rid_pipe_reg = {ID_WIDTH{1'b0}};
reg [DATA_WIDTH-1:0] s_axi_rdata_pipe_reg = {DATA_WIDTH{1'b0}};
reg s_axi_rlast_pipe_reg = 1'b0;
reg s_axi_rvalid_pipe_reg = 1'b0;

// (* RAM_STYLE="BLOCK" *)
reg [DATA_WIDTH-1:0] mem[(2**VALID_ADDR_WIDTH)-1:0];

/* 
wire [VALID_ADDR_WIDTH-1:0] s_axi_awaddr_valid = s_axi_awaddr >> (ADDR_WIDTH - VALID_ADDR_WIDTH);
wire [VALID_ADDR_WIDTH-1:0] s_axi_araddr_valid = s_axi_araddr >> (ADDR_WIDTH - VALID_ADDR_WIDTH);
wire [VALID_ADDR_WIDTH-1:0] read_addr_valid = read_addr_reg >> (ADDR_WIDTH - VALID_ADDR_WIDTH);
wire [VALID_ADDR_WIDTH-1:0] write_addr_valid = write_addr_reg >> (ADDR_WIDTH - VALID_ADDR_WIDTH);
*/
wire [7:0] s_axi_awaddr_valid = { {(8-VALID_ADDR_WIDTH){1'b0}}, s_axi_awaddr >> (ADDR_WIDTH - VALID_ADDR_WIDTH) };
wire [7:0] s_axi_araddr_valid = { {(8-VALID_ADDR_WIDTH){1'b0}}, s_axi_araddr >> (ADDR_WIDTH - VALID_ADDR_WIDTH) };
wire [7:0] read_addr_valid = { {(8-VALID_ADDR_WIDTH){1'b0}}, read_addr_reg >> (ADDR_WIDTH - VALID_ADDR_WIDTH) };
wire [7:0] write_addr_valid = { {(8-VALID_ADDR_WIDTH){1'b0}}, write_addr_reg >> (ADDR_WIDTH - VALID_ADDR_WIDTH) };

assign s_axi_awready = s_axi_awready_reg;
assign s_axi_wready = s_axi_wready_reg;
assign s_axi_bid = s_axi_bid_reg;
assign s_axi_bresp = 2'b00;
assign s_axi_bvalid = s_axi_bvalid_reg;
assign s_axi_arready = s_axi_arready_reg;
assign s_axi_rid = PIPELINE_OUTPUT ? s_axi_rid_pipe_reg : s_axi_rid_reg;
assign s_axi_rdata = PIPELINE_OUTPUT ? s_axi_rdata_pipe_reg : s_axi_rdata_reg;
assign s_axi_rresp = 2'b00;
assign s_axi_rlast = PIPELINE_OUTPUT ? s_axi_rlast_pipe_reg : s_axi_rlast_reg;
assign s_axi_rvalid = PIPELINE_OUTPUT ? s_axi_rvalid_pipe_reg : s_axi_rvalid_reg;

integer i, j;

initial begin
    // two nested loops for smaller number of iterations per loop
    // workaround for synthesizer complaints about large loop counts
    for (i = 0; i < 2**VALID_ADDR_WIDTH; i = i + 2**(VALID_ADDR_WIDTH/2)) begin
        for (j = i; j < i + 2**(VALID_ADDR_WIDTH/2); j = j + 1) begin
            mem[j] = 0;
        end
    end
end

always @* begin
    write_state_next = WRITE_STATE_IDLE;

    mem_wr_en = 1'b0;

    write_id_next = write_id_reg;
    write_addr_next = write_addr_reg;
    write_count_next = write_count_reg;
    write_size_next = write_size_reg;
    write_burst_next = write_burst_reg;

    s_axi_awready_next = 1'b0;
    s_axi_wready_next = 1'b0;
    s_axi_bid_next = s_axi_bid_reg;
    s_axi_bvalid_next = s_axi_bvalid_reg && !s_axi_bready;

    case (write_state_reg)
        WRITE_STATE_IDLE: begin
            s_axi_awready_next = 1'b1;

            if (s_axi_awready && s_axi_awvalid) begin
                write_id_next = s_axi_awid;
                write_addr_next = s_axi_awaddr;
                write_count_next = s_axi_awlen;
                write_size_next = s_axi_awsize < $clog2(STRB_WIDTH) ? s_axi_awsize : $clog2(STRB_WIDTH);
                write_burst_next = s_axi_awburst;

                s_axi_awready_next = 1'b0;
                s_axi_wready_next = 1'b1;
                write_state_next = WRITE_STATE_BURST;
            end else begin
                write_state_next = WRITE_STATE_IDLE;
            end
        end
        WRITE_STATE_BURST: begin
            s_axi_wready_next = 1'b1;
            if (s_axi_wready && s_axi_wvalid) begin
                mem_wr_en = 1'b1;
                if (write_burst_reg != 2'b00) begin
                    write_addr_next = write_addr_reg + (1 << write_size_reg);
                end
                write_count_next = write_count_reg - 1;
                if (write_count_reg > 0) begin
                    write_state_next = WRITE_STATE_BURST;
                end else begin
                    s_axi_wready_next = 1'b0;
                    if (s_axi_bready || !s_axi_bvalid) begin
                        s_axi_bid_next = write_id_reg;
                        s_axi_bvalid_next = 1'b1;
                        s_axi_awready_next = 1'b1;
                        write_state_next = WRITE_STATE_IDLE;
                    end else begin
                        write_state_next = WRITE_STATE_RESP;
                    end
                end
            end else begin
                write_state_next = WRITE_STATE_BURST;
            end
        end
        WRITE_STATE_RESP: begin
            if (s_axi_bready || !s_axi_bvalid) begin
                s_axi_bid_next = write_id_reg;
                s_axi_bvalid_next = 1'b1;
                s_axi_awready_next = 1'b1;
                write_state_next = WRITE_STATE_IDLE;
            end else begin
                write_state_next = WRITE_STATE_RESP;
            end
        end
    endcase
end

always @(posedge clk) begin
    if (rst) begin
        s_axi_awready_reg <= 1'b0;
        s_axi_wready_reg <= 1'b0;
        s_axi_bvalid_reg <= 1'b0;
        write_state_reg <= WRITE_STATE_IDLE;
    end
    else begin
        write_state_reg <= write_state_next;

        write_id_reg <= write_id_next;
        write_addr_reg <= write_addr_next;
        write_count_reg <= write_count_next;
        write_size_reg <= write_size_next;
        write_burst_reg <= write_burst_next;

        s_axi_awready_reg <= s_axi_awready_next;
        s_axi_wready_reg <= s_axi_wready_next;
        s_axi_bid_reg <= s_axi_bid_next;
        s_axi_bvalid_reg <= s_axi_bvalid_next;

        if (mem_wr_en) begin
            for (i = 0; i < WORD_WIDTH; i = i + 1) begin
                if (s_axi_wstrb[i]) begin
                    mem[write_addr_valid][WORD_SIZE*i +: WORD_SIZE] <= s_axi_wdata[WORD_SIZE*i +: WORD_SIZE];
                end
            end
        end
    end

end

always @* begin
    read_state_next = READ_STATE_IDLE;

    mem_rd_en = 1'b0;

    s_axi_rid_next = s_axi_rid_reg;
    s_axi_rlast_next = s_axi_rlast_reg;
    s_axi_rvalid_next = s_axi_rvalid_reg && !(s_axi_rready || (PIPELINE_OUTPUT && !s_axi_rvalid_pipe_reg));

    read_id_next = read_id_reg;
    read_addr_next = read_addr_reg;
    read_count_next = read_count_reg;
    read_size_next = read_size_reg;
    read_burst_next = read_burst_reg;

    s_axi_arready_next = 1'b0;

    case (read_state_reg)
        READ_STATE_IDLE: begin
            s_axi_arready_next = 1'b1;

            if (s_axi_arready && s_axi_arvalid) begin
                read_id_next = s_axi_arid;
                read_addr_next = s_axi_araddr;
                read_count_next = s_axi_arlen;
                read_size_next = s_axi_arsize < $clog2(STRB_WIDTH) ? s_axi_arsize : $clog2(STRB_WIDTH);
                read_burst_next = s_axi_arburst;

                s_axi_arready_next = 1'b0;
                read_state_next = READ_STATE_BURST;
            end else begin
                read_state_next = READ_STATE_IDLE;
            end
        end
        READ_STATE_BURST: begin
            if (s_axi_rready || (PIPELINE_OUTPUT && !s_axi_rvalid_pipe_reg) || !s_axi_rvalid_reg) begin
                mem_rd_en = 1'b1;
                s_axi_rvalid_next = 1'b1;
                s_axi_rid_next = read_id_reg;
                s_axi_rlast_next = (read_count_reg == 0);
                if (read_burst_reg != 2'b00) begin
                    read_addr_next = read_addr_reg + (1 << read_size_reg);
                end
                read_count_next = read_count_reg - 1;
                if (read_count_reg > 0) begin
                    read_state_next = READ_STATE_BURST;
                end else begin
                    s_axi_arready_next = 1'b1;
                    read_state_next = READ_STATE_IDLE;
                end
            end else begin
                read_state_next = READ_STATE_BURST;
            end
        end
    endcase
end

always @(posedge clk) begin
    if (rst) begin
        s_axi_arready_reg <= 1'b0;
        s_axi_rvalid_reg <= 1'b0;
        s_axi_rvalid_pipe_reg <= 1'b0;
        read_state_reg <= READ_STATE_IDLE;
    end
    else begin
        read_state_reg <= read_state_next;

        read_id_reg <= read_id_next;
        read_addr_reg <= read_addr_next;
        read_count_reg <= read_count_next;
        read_size_reg <= read_size_next;
        read_burst_reg <= read_burst_next;

        s_axi_arready_reg <= s_axi_arready_next;
        s_axi_rid_reg <= s_axi_rid_next;
        s_axi_rlast_reg <= s_axi_rlast_next;
        s_axi_rvalid_reg <= s_axi_rvalid_next;
        
        if (!s_axi_rvalid_pipe_reg || s_axi_rready) begin
            s_axi_rid_pipe_reg <= s_axi_rid_reg;
            s_axi_rdata_pipe_reg <= s_axi_rdata_reg;
            s_axi_rlast_pipe_reg <= s_axi_rlast_reg;
            s_axi_rvalid_pipe_reg <= s_axi_rvalid_reg;
        end
    end

end

// PIM_MODEL instance and control
wire p_en = !mem_wr_en && !mem_rd_en; // Processing Enable

reg [255:0] rwl ;
reg [DATA_WIDTH-1:0] adc_out [0:PWIDTH-1];
reg [5-1:0]      shift_cnt;
reg [DATA_WIDTH-1:0] acc_result [0:PWIDTH-1];
reg [DATA_WIDTH-1:0] sum_acc_result;
reg [DATA_WIDTH-1:0] mac_out_reg;

always@(posedge clk) begin
    if(!p_en) begin // Processing Disabled -> Memory operation
        if (mem_wr_en) begin
            for (i = 0; i < WORD_WIDTH; i = i + 1) begin
                if (s_axi_wstrb[i]) begin
                    mem[write_addr_valid][WORD_SIZE*i +: WORD_SIZE] <= s_axi_wdata[WORD_SIZE*i +: WORD_SIZE];
                end
            end
        end           
        else if (mem_rd_en) begin // Memory Read Enable
            s_axi_rdata_reg <= mem[read_addr_valid];
        end
        // ** initialize accumulation **
        shift_cnt <= 0;
        for(i = 0; i < PWIDTH; i=i+1) begin
            acc_result[i] <= 0;
        end
    end 
    else begin // Processing Enabled -> MAC operation
        for(i = 0; i < PWIDTH; i=i+1) begin
            acc_result[i] <= (shift_cnt == 0) ? adc_out[i] : acc_result[i] + (adc_out[i] << shift_cnt);
        end
        shift_cnt <= shift_cnt + 1;
    end
    mac_out_reg <= sum_acc_result;
end
assign mac_out = mac_out_reg;

always@(rwl) begin // ADC Output is modeled
    for(i = 0; i < PWIDTH; i=i+1) begin
        adc_out[i] = 0;
        for(j = 0; j < PDEPTH; j=j+1) begin
            adc_out[i] = adc_out[i] + (mem[PIM_ADDR_BEGIN+j][i] & rwl[j]);
        end
    end
end

always@(*) begin
    sum_acc_result = 0;
    for(i = 0; i < PWIDTH; i=i+1) begin
        sum_acc_result = sum_acc_result + (acc_result[i] << i);
    end
end

always @(posedge clk) begin       
    if (rst) begin
        rwl <= 256'd0;  // Clear all on reset
    end 
    else begin
        for (i = 0; i < 256; i = i + 1) begin
            rwl[i] <= $random % 2;  // Each bit randomly set to 0 or 1
        end
    end

	if (p_en) begin
		$display("---- Operation ----");
		$display("p_en:%h, mem_wr_en:%h", p_en, mem_wr_en);
		$display("input: %h, mac_out:%h\n", s_axi_wdata, mac_out);
	end
	else begin
		if (mem_wr_en) begin
			$display("==== Writing ====");
			$display("p_en:%d, mem_wr_en:%h, address %h, s_axi_wdata:%h\n", p_en, mem_wr_en, write_addr_valid, s_axi_wdata);
		end
		else begin
			$display("~~~~ Reading ~~~~");
			$display("p_en:%d, mem_rd_en:%h, address %h, s_axi_rdata:%h\n", p_en, mem_rd_en, read_addr_valid, s_axi_rdata);
		end
	end
end

endmodule

`resetall

syn/iverilog/0518/tb_axi_pim.v
`timescale 1ns / 1ps

module tb_axi_pim();

    // Parameters
    parameter PIM_ADDR_BEGIN = 'h000;
    parameter DATA_WIDTH = 32;
    parameter ADDR_WIDTH = 8;
    parameter PWIDTH = 32;
    parameter STRB_WIDTH = DATA_WIDTH / 8;
    parameter ID_WIDTH = 8;
    parameter BURST_LENGTH = 4; 
    parameter CLOCK_PERIOD = 10; 
    parameter PDEPTH = (1<<ADDR_WIDTH);

    // Clock and reset
    reg clk = 0;
    reg rst = 1;

    // AXI signals
    reg [ID_WIDTH-1:0] s_axi_awid;
    reg [ADDR_WIDTH-1:0] s_axi_awaddr;
    reg [7:0] s_axi_awlen;
    reg [2:0] s_axi_awsize;
    reg [1:0] s_axi_awburst;
    reg s_axi_awlock;
    reg [3:0] s_axi_awcache;
    reg [2:0] s_axi_awprot;
    reg s_axi_awvalid;
    wire s_axi_awready;
    reg [DATA_WIDTH-1:0] s_axi_wdata;
    reg [STRB_WIDTH-1:0] s_axi_wstrb;
    reg s_axi_wlast;
    reg s_axi_wvalid;
    wire s_axi_wready;
    wire [ID_WIDTH-1:0] s_axi_bid;
    wire [1:0] s_axi_bresp;
    wire s_axi_bvalid;
    reg s_axi_bready;
    reg [ID_WIDTH-1:0] s_axi_arid;
    reg [ADDR_WIDTH-1:0] s_axi_araddr;
    reg [7:0] s_axi_arlen;
    reg [2:0] s_axi_arsize;
    reg [1:0] s_axi_arburst;
    reg s_axi_arlock;
    reg [3:0] s_axi_arcache;
    reg [2:0] s_axi_arprot;
    reg s_axi_arvalid;
    wire s_axi_arready;
    wire [ID_WIDTH-1:0] s_axi_rid;
    wire [DATA_WIDTH-1:0] s_axi_rdata;
    wire [1:0] s_axi_rresp;
    wire s_axi_rlast;
    wire s_axi_rvalid;
    reg s_axi_rready;
    wire [PWIDTH-1:0] q;
    wire [DATA_WIDTH-1:0] mac_out;

    // Instantiate the Unit Under Test (UUT)
    axi_pim #(
        .PIM_ADDR_BEGIN(PIM_ADDR_BEGIN),
        .DATA_WIDTH(DATA_WIDTH),
        .ADDR_WIDTH(ADDR_WIDTH),
        .STRB_WIDTH(STRB_WIDTH),
        .ID_WIDTH(ID_WIDTH),
        .PIPELINE_OUTPUT(0),
        .PWIDTH(PWIDTH),
        .PDEPTH(PDEPTH)
    ) uut (
        .clk(clk),
        .rst(rst),
        .s_axi_awid(s_axi_awid),
        .s_axi_awaddr(s_axi_awaddr),
        .s_axi_awlen(s_axi_awlen),
        .s_axi_awsize(s_axi_awsize),
        .s_axi_awburst(s_axi_awburst),
        .s_axi_awlock(s_axi_awlock),
        .s_axi_awcache(s_axi_awcache),
        .s_axi_awprot(s_axi_awprot),
        .s_axi_awvalid(s_axi_awvalid),
        .s_axi_awready(s_axi_awready),
        .s_axi_wdata(s_axi_wdata),
        .s_axi_wstrb(s_axi_wstrb),
        .s_axi_wlast(s_axi_wlast),
        .s_axi_wvalid(s_axi_wvalid),
        .s_axi_wready(s_axi_wready),
        .s_axi_bid(s_axi_bid),
        .s_axi_bresp(s_axi_bresp),
        .s_axi_bvalid(s_axi_bvalid),
        .s_axi_bready(s_axi_bready),
        .s_axi_arid(s_axi_arid),
        .s_axi_araddr(s_axi_araddr),
        .s_axi_arlen(s_axi_arlen),
        .s_axi_arsize(s_axi_arsize),
        .s_axi_arburst(s_axi_arburst),
        .s_axi_arlock(s_axi_arlock),
        .s_axi_arcache(s_axi_arcache),
        .s_axi_arprot(s_axi_arprot),
        .s_axi_arvalid(s_axi_arvalid),
        .s_axi_arready(s_axi_arready),
        .s_axi_rid(s_axi_rid),
        .s_axi_rdata(s_axi_rdata),
        .s_axi_rresp(s_axi_rresp),
        .s_axi_rlast(s_axi_rlast),
        .s_axi_rvalid(s_axi_rvalid),
        .s_axi_rready(s_axi_rready),
        .mac_out(mac_out)
    );

    // Clock generation
    always #(CLOCK_PERIOD / 2) clk = ~clk;

    // Reset generation
    initial begin
        // Initialize Inputs
        s_axi_awid = 0;
        s_axi_awaddr = 0;
        s_axi_awlen = BURST_LENGTH - 1;
        s_axi_awsize = 2; // Corresponding to DATA_WIDTH of 32 bits
        s_axi_awburst = 2'b01; // INCR type
        s_axi_awlock = 0;
        s_axi_awcache = 0;
        s_axi_awprot = 0;
        s_axi_awvalid = 0;
        s_axi_wdata = 0;
        s_axi_wstrb = {STRB_WIDTH{1'b1}}; // All bytes are valid
        s_axi_wlast = 0;
        s_axi_wvalid = 0;
        s_axi_bready = 0;
        s_axi_arid = 0;
        s_axi_araddr = 0;
        s_axi_arlen = BURST_LENGTH - 1;
        s_axi_arsize = 2; // Corresponding to DATA_WIDTH of 32 bits
        s_axi_arburst = 2'b01; // INCR type
        s_axi_arlock = 0;
        s_axi_arcache = 0;
        s_axi_arprot = 0;
        s_axi_arvalid = 0;
        s_axi_rready = 0;

        // Wait 100 ns for global reset to finish
        #100;
        rst = 0;

        // Add stimulus here
        test_burst_write_and_read();

        // Complete
        $finish;
    end

    // Test functions
    task test_burst_write_and_read;
        integer i;
        begin
            // Burst Write
            @(posedge clk);
            s_axi_awid = 1;
            s_axi_awaddr = 16'h0000;
            s_axi_awlen = BURST_LENGTH - 1; // 4-bit burst
            s_axi_awsize = $clog2(DATA_WIDTH/8);
            s_axi_awburst = 2'b01; // INCR
            s_axi_awvalid = 1;
            @(posedge clk);
            s_axi_awvalid = 0;

            for (i = 0; i < BURST_LENGTH; i = i + 1) begin
                @(posedge clk);
                s_axi_wdata = 32'hDEAD_BEEF + i;
                s_axi_wstrb = {STRB_WIDTH{1'b1}};
                s_axi_wvalid = 1;
                s_axi_wlast = (i == BURST_LENGTH - 1) ? 1'b1 : 1'b0;
                @(posedge clk);
            end
            s_axi_wvalid = 0;
            s_axi_wlast = 0;

            s_axi_bready = 1;
            @(posedge clk);
            s_axi_bready = 0;

            // Burst Read
            @(posedge clk);
            s_axi_arid = 1;
            s_axi_araddr = 16'h0000;
            s_axi_arlen = BURST_LENGTH - 1; // 4-beat burst
            s_axi_arsize = $clog2(DATA_WIDTH/8);
            s_axi_arburst = 2'b01; // INCR
            s_axi_arvalid = 1;
            @(posedge clk);
            s_axi_arvalid = 0;

            for (i = 0; i < BURST_LENGTH; i = i + 1) begin
                @(posedge clk);
                s_axi_rready = 1;
                @(posedge clk);
                // Check received data
                if (s_axi_rdata != 32'hDEAD_BEEF + i) begin
                    $display("Mismatch in data received: expected %h, got %h", s_axi_wdata, s_axi_rdata);
                end
                if (s_axi_rlast && (i != BURST_LENGTH - 1)) begin
                    $display("Early rlast at index %d", i);
                end
                if (i == BURST_LENGTH - 1 && !s_axi_rlast) begin
                    $display("Missing rlast at the end of the burst");
                end
            end
            s_axi_rready = 0;
        end
    endtask

	initial begin
		$dumpvars(2, uut);
		$dumpfile("axi_pim.vcd");
	end

endmodule

syn/iverilog/0518/dump.vcd
$date
	Sat May 18 19:43:50 2024
$end
$version
	Icarus Verilog
$end
$timescale
	1ps
$end
$scope module tb_axi_pim $end
$scope module uut $end
$var wire 1 ! clk $end
$var wire 32 " mac_out [31:0] $end
$var wire 1 # p_en $end
$var wire 1 $ rst $end
$var wire 8 % s_axi_araddr [7:0] $end
$var wire 2 & s_axi_arburst [1:0] $end
$var wire 4 ' s_axi_arcache [3:0] $end
$var wire 8 ( s_axi_arid [7:0] $end
$var wire 8 ) s_axi_arlen [7:0] $end
$var wire 1 * s_axi_arlock $end
$var wire 3 + s_axi_arprot [2:0] $end
$var wire 1 , s_axi_arready $end
$var wire 3 - s_axi_arsize [2:0] $end
$var wire 1 . s_axi_arvalid $end
$var wire 8 / s_axi_awaddr [7:0] $end
$var wire 2 0 s_axi_awburst [1:0] $end
$var wire 4 1 s_axi_awcache [3:0] $end
$var wire 8 2 s_axi_awid [7:0] $end
$var wire 8 3 s_axi_awlen [7:0] $end
$var wire 1 4 s_axi_awlock $end
$var wire 3 5 s_axi_awprot [2:0] $end
$var wire 1 6 s_axi_awready $end
$var wire 3 7 s_axi_awsize [2:0] $end
$var wire 1 8 s_axi_awvalid $end
$var wire 8 9 s_axi_bid [7:0] $end
$var wire 1 : s_axi_bready $end
$var wire 2 ; s_axi_bresp [1:0] $end
$var wire 1 < s_axi_bvalid $end
$var wire 32 = s_axi_rdata [31:0] $end
$var wire 8 > s_axi_rid [7:0] $end
$var wire 1 ? s_axi_rlast $end
$var wire 1 @ s_axi_rready $end
$var wire 2 A s_axi_rresp [1:0] $end
$var wire 1 B s_axi_rvalid $end
$var wire 32 C s_axi_wdata [31:0] $end
$var wire 1 D s_axi_wlast $end
$var wire 1 E s_axi_wready $end
$var wire 4 F s_axi_wstrb [3:0] $end
$var wire 1 G s_axi_wvalid $end
$var wire 8 H write_addr_valid [7:0] $end
$var wire 8 I s_axi_awaddr_valid [7:0] $end
$var wire 8 J s_axi_araddr_valid [7:0] $end
$var wire 8 K read_addr_valid [7:0] $end
$var reg 32 L mac_out_reg [31:0] $end
$var reg 1 M mem_rd_en $end
$var reg 1 N mem_wr_en $end
$var reg 8 O read_addr_next [7:0] $end
$var reg 8 P read_addr_reg [7:0] $end
$var reg 2 Q read_burst_next [1:0] $end
$var reg 2 R read_burst_reg [1:0] $end
$var reg 8 S read_count_next [7:0] $end
$var reg 8 T read_count_reg [7:0] $end
$var reg 8 U read_id_next [7:0] $end
$var reg 8 V read_id_reg [7:0] $end
$var reg 3 W read_size_next [2:0] $end
$var reg 3 X read_size_reg [2:0] $end
$var reg 1 Y read_state_next $end
$var reg 1 Z read_state_reg $end
$var reg 256 [ rwl [255:0] $end
$var reg 1 \ s_axi_arready_next $end
$var reg 1 ] s_axi_arready_reg $end
$var reg 1 ^ s_axi_awready_next $end
$var reg 1 _ s_axi_awready_reg $end
$var reg 8 ` s_axi_bid_next [7:0] $end
$var reg 8 a s_axi_bid_reg [7:0] $end
$var reg 1 b s_axi_bvalid_next $end
$var reg 1 c s_axi_bvalid_reg $end
$var reg 32 d s_axi_rdata_pipe_reg [31:0] $end
$var reg 32 e s_axi_rdata_reg [31:0] $end
$var reg 8 f s_axi_rid_next [7:0] $end
$var reg 8 g s_axi_rid_pipe_reg [7:0] $end
$var reg 8 h s_axi_rid_reg [7:0] $end
$var reg 1 i s_axi_rlast_next $end
$var reg 1 j s_axi_rlast_pipe_reg $end
$var reg 1 k s_axi_rlast_reg $end
$var reg 1 l s_axi_rvalid_next $end
$var reg 1 m s_axi_rvalid_pipe_reg $end
$var reg 1 n s_axi_rvalid_reg $end
$var reg 1 o s_axi_wready_next $end
$var reg 1 p s_axi_wready_reg $end
$var reg 5 q shift_cnt [4:0] $end
$var reg 32 r sum_acc_result [31:0] $end
$var reg 8 s write_addr_next [7:0] $end
$var reg 8 t write_addr_reg [7:0] $end
$var reg 2 u write_burst_next [1:0] $end
$var reg 2 v write_burst_reg [1:0] $end
$var reg 8 w write_count_next [7:0] $end
$var reg 8 x write_count_reg [7:0] $end
$var reg 8 y write_id_next [7:0] $end
$var reg 8 z write_id_reg [7:0] $end
$var reg 3 { write_size_next [2:0] $end
$var reg 3 | write_size_reg [2:0] $end
$var reg 2 } write_state_next [1:0] $end
$var reg 2 ~ write_state_reg [1:0] $end
$var integer 32 !" i [31:0] $end
$var integer 32 "" j [31:0] $end
$upscope $end
$upscope $end
$enddefinitions $end
#0
$dumpvars
b1000000 ""
b1000000 !"
b0 ~
b0 }
b0 |
b0 {
b0 z
b0 y
b0 x
b0 w
b0 v
b0 u
b0 t
b0 s
bx r
bx q
0p
0o
0n
0m
0l
0k
0j
0i
b0 h
b0 g
b0 f
b0 e
b0 d
0c
0b
b0 a
b0 `
0_
1^
0]
1\
bx [
0Z
0Y
b0 X
b0 W
b0 V
b0 U
b0 T
b0 S
b0 R
b0 Q
b0 P
b0 O
0N
0M
bx L
b0 K
b0 J
b0 I
b0 H
0G
b1111 F
0E
0D
b0 C
0B
b0 A
0@
0?
b0 >
b0 =
0<
b0 ;
0:
b0 9
08
b10 7
06
b0 5
04
b11 3
b0 2
b0 1
b1 0
b0 /
0.
b10 -
0,
b0 +
0*
b11 )
b0 (
b0 '
b1 &
b0 %
1$
1#
bx "
0!
$end
#5000
b100000000 ""
b0 [
b100000 !"
1!
#10000
0!
#15000
b100000 !"
1!
#20000
0!
#25000
b100000 !"
1!
#30000
0!
#35000
b100000 !"
1!
#40000
0!
#45000
b100000 !"
1!
#50000
0!
#55000
b100000 !"
1!
#60000
0!
#65000
b100000 !"
1!
#70000
0!
#75000
b100000 !"
1!
#80000
0!
#85000
b100000 !"
1!
#90000
0!
#95000
b100000 !"
1!
#100000
0!
0$
#105000
b1 }
1o
b1 u
b10 {
b11 w
b1 y
1\
b100000000 ""
16
1_
1,
1]
b1110111101100010000100100011100100100100110000110111110011101110000100001101000100100011000110001100100011111010010001001100010001111011001101111100000001110111110011000011011101101100111001111100000110010000011100111110100001111010001011010101101101111110 [
0^
b100000 !"
18
b1 2
1!
#110000
0!
